condor_support/CondorLog.py
condor_support/CondorMetric.py
condor_support/DqrLog.py
condor_support/__init__.py
condor_support/_version.py
condor_support/condor_history_scraper.py
condor_support/dag-metrics.py
condor_support/log-scraper.py
condor_support/log-stats.py
condor_support-0.0.2.dist-info/licenses/LICENSE
condor_support-0.0.2.dist-info/METADATA
condor_support-0.0.2.dist-info/WHEEL
condor_support-0.0.2.dist-info/entry_points.txt
condor_support-0.0.2.dist-info/top_level.txt
condor_support-0.0.2.dist-info/RECORD
