Metadata-Version: 2.4
Name: condor_support
Version: 0.0.2
Summary: Utilities to analyze and fill gaps in omicron triggers
Author-email: Joseph Areeda <joseph.areeda@ligo.org>
Project-URL: Bug Tracker, https://git.ligo.org/joseph-areeda/omicron-gap/-/issues
Project-URL: Source Code, https://git.ligo.org/joseph-areeda/omicron-gap.git
Classifier: Development Status :: 4 - Beta
Classifier: Intended Audience :: Science/Research
Classifier: License :: OSI Approved :: GNU General Public License v3 or later (GPLv3+)
Classifier: Natural Language :: English
Classifier: Operating System :: OS Independent
Classifier: Programming Language :: Python
Classifier: Programming Language :: Python :: 3
Classifier: Programming Language :: Python :: 3.10
Classifier: Programming Language :: Python :: 3.11
Classifier: Topic :: Scientific/Engineering :: Astronomy
Classifier: Topic :: Scientific/Engineering :: Physics
Requires-Python: >=3.10
License-File: LICENSE
Requires-Dist: ligotimegps>=1.2.1
Requires-Dist: gwpy>=3.0.7
Requires-Dist: matplotlib>=3.3.0
Requires-Dist: numpy
Requires-Dist: astropy
Requires-Dist: python-dateutil
Requires-Dist: pytz
Requires-Dist: gpstime
Requires-Dist: ja-webutils
Requires-Dist: htcondor
Dynamic: license-file
